halko/__init__.py
halko/functions.py
halko/main.py
halko/shared.cpython-311-darwin.so
halkoSVD-0.2.4.dist-info/LICENSE
halkoSVD-0.2.4.dist-info/METADATA
halkoSVD-0.2.4.dist-info/WHEEL
halkoSVD-0.2.4.dist-info/entry_points.txt
halkoSVD-0.2.4.dist-info/top_level.txt
halkoSVD-0.2.4.dist-info/RECORD
