Metadata-Version: 2.1
Name: halkoSVD
Version: 0.2.4
Summary: Fast Python/Cython implementation of the PCAone Halko algorithm
Home-page: https://github.com/Rosemeis/halkoSVD
Author: Jonas Meisner
Author-email: meisnerucph@gmail.com
Classifier: Programming Language :: Python :: 3
Classifier: License :: OSI Approved :: GNU General Public License v3 (GPLv3)
Classifier: Operating System :: OS Independent
Classifier: Development Status :: 3 - Alpha
Requires-Python: >=3.7
License-File: LICENSE
Requires-Dist: cython >3.0.0
Requires-Dist: numpy >2.0.0
